Metadata-Version: 2.1
Name: django-mp-orders
Version: 1.0.7
Summary: Django orders apps
Home-page: https://github.com/pmaigutyak/mp-orders
Author: Paul Maigutyak
Author-email: pmaigutyak@gmail.com
License: MIT
Download-URL: https://github.com/pmaigutyak/mp-orders/archive/1.0.7.tar.gz
Platform: UNKNOWN
